blib/__init__.py
blib/banner.py
blib/code.py
blib/draw.py
blib/files.py
blib/index.py
blib/layer.py
blib/parser.py
blib/rgba.py
blib/utils.py
blib/vec3.py
blib-0.0.3.dist-info/LICENSE
blib-0.0.3.dist-info/METADATA
blib-0.0.3.dist-info/WHEEL
blib-0.0.3.dist-info/top_level.txt
blib-0.0.3.dist-info/RECORD
