Metadata-Version: 2.1
Name: blib
Version: 0.0.3
Summary: Package for drawing images of M@B Bannerlord banners from community created banner codes.
Home-page: https://github.com/Niklas-Seppala/blib
Author: Niklas Seppälä
License: UNKNOWN
Platform: UNKNOWN
Classifier: Intended Audience :: Developers
Classifier: Programming Language :: Python
Requires-Dist: numpy
Requires-Dist: pillow
